LICENSE
MANIFEST.in
README.md
requirements.txt
setup.py
oxasl_optpcasl/__init__.py
oxasl_optpcasl/_version.py
oxasl_optpcasl/cost.py
oxasl_optpcasl/kinetic_model.py
oxasl_optpcasl/main.py
oxasl_optpcasl/optimize.py
oxasl_optpcasl/scan.py
oxasl_optpcasl/structures.py
oxasl_optpcasl.egg-info/PKG-INFO
oxasl_optpcasl.egg-info/SOURCES.txt
oxasl_optpcasl.egg-info/dependency_links.txt
oxasl_optpcasl.egg-info/entry_points.txt
oxasl_optpcasl.egg-info/requires.txt
oxasl_optpcasl.egg-info/top_level.txt
oxasl_optpcasl/gui/__init__.py
oxasl_optpcasl/gui/banner.png
oxasl_optpcasl/gui/icon.png
oxasl_optpcasl/gui/main_window.py
oxasl_optpcasl/gui/optimizer_options.py
oxasl_optpcasl/gui/oxasl.png
oxasl_optpcasl/gui/phys_params.py
oxasl_optpcasl/gui/runner.py
oxasl_optpcasl/gui/scan_options.py
oxasl_optpcasl/gui/scan_summary.py
oxasl_optpcasl/gui/sensitivity_plot.py
oxasl_optpcasl/gui/widgets.py
oxasl_optpcasl/test/__init__.py
oxasl_optpcasl/test/test_optimize.py