Metadata-Version: 2.2
Name: oxasl-optpcasl
Version: 0.0.4
Summary: Python library for optimizing multi-PLD pCASL acquisitions
Home-page: https://oxasl_optpcasl.readthedocs.io/
Author: Joseph Woods, Martin Craig
Author-email: martin.craig@eng.ox.ac.uk
License: Apache-2.0
Classifier: Development Status :: 3 - Alpha
Classifier: Intended Audience :: Science/Research
Classifier: Programming Language :: Python :: 2.7
Classifier: Programming Language :: Python :: 3
Classifier: Topic :: Scientific/Engineering :: Bio-Informatics
Classifier: License :: OSI Approved :: Apache Software License
License-File: LICENSE
Requires-Dist: numpy
Requires-Dist: tabulate
Requires-Dist: sphinx
Requires-Dist: oxasl>=0.1.12
Dynamic: author
Dynamic: author-email
Dynamic: classifier
Dynamic: description
Dynamic: description-content-type
Dynamic: home-page
Dynamic: license
Dynamic: requires-dist
Dynamic: summary
